AUTHORS
ChangeLog
MANIFEST.in
README.rst
requirements.txt
setup.cfg
setup.py
bughunter.egg-info/PKG-INFO
bughunter.egg-info/SOURCES.txt
bughunter.egg-info/dependency_links.txt
bughunter.egg-info/entry_points.txt
bughunter.egg-info/not-zip-safe
bughunter.egg-info/pbr.json
bughunter.egg-info/top_level.txt
dist/bughunter-1.5.0.dev2.linux-x86_64.tar.gz
doc/.DS_Store
doc/Makefile
doc/conf.py
doc/contributing.rst
doc/example.py
doc/gmr.rst
doc/heat-templates.rst
doc/index.rst
doc/magnum-proxy.rst
doc/make.bat
doc/objects.rst
doc/_build/doctrees/contributing.doctree
doc/_build/doctrees/environment.pickle
doc/_build/doctrees/gmr.doctree
doc/_build/doctrees/heat-templates.doctree
doc/_build/doctrees/index.doctree
doc/_build/doctrees/magnum-proxy.doctree
doc/_build/doctrees/objects.doctree
doc/_build/doctrees/dev/dev-bay-template-example.doctree
doc/_build/doctrees/dev/dev-build-atomic-image.doctree
doc/_build/doctrees/dev/dev-heat-mesos.doctree
doc/_build/doctrees/dev/dev-kubernetes-load-balancer.doctree
doc/_build/doctrees/dev/dev-manual-devstack.doctree
doc/_build/doctrees/dev/dev-quickstart.doctree
doc/_build/doctrees/dev/dev-tls.doctree
doc/_build/html/.buildinfo
doc/_build/html/contributing.html
doc/_build/html/genindex.html
doc/_build/html/gmr.html
doc/_build/html/heat-templates.html
doc/_build/html/index.html
doc/_build/html/magnum-proxy.html
doc/_build/html/objects.html
doc/_build/html/objects.inv
doc/_build/html/search.html
doc/_build/html/searchindex.js
doc/_build/html/_sources/contributing.txt
doc/_build/html/_sources/gmr.txt
doc/_build/html/_sources/heat-templates.txt
doc/_build/html/_sources/index.txt
doc/_build/html/_sources/magnum-proxy.txt
doc/_build/html/_sources/objects.txt
doc/_build/html/_sources/dev/dev-bay-template-example.txt
doc/_build/html/_sources/dev/dev-build-atomic-image.txt
doc/_build/html/_sources/dev/dev-heat-mesos.txt
doc/_build/html/_sources/dev/dev-kubernetes-load-balancer.txt
doc/_build/html/_sources/dev/dev-manual-devstack.txt
doc/_build/html/_sources/dev/dev-quickstart.txt
doc/_build/html/_sources/dev/dev-tls.txt
doc/_build/html/_static/ajax-loader.gif
doc/_build/html/_static/alabaster.css
doc/_build/html/_static/basic.css
src/buhunter.egg-info/PKG-INFO
src/buhunter.egg-info/SOURCES.txt
src/buhunter.egg-info/dependency_links.txt
src/buhunter.egg-info/top_level.txt
src/demo.egg-info/PKG-INFO
src/demo.egg-info/SOURCES.txt
src/demo.egg-info/dependency_links.txt
src/demo.egg-info/top_level.txt
src/lol.egg-info/PKG-INFO
src/lol.egg-info/SOURCES.txt
src/lol.egg-info/dependency_links.txt
src/lol.egg-info/top_level.txt