Metadata-Version: 1.0
Name: bughunter
Version: 0.0.3
Summary: Service
Home-page: UNKNOWN
Author: BugHunter
Author-email: 1394812183@qq.com
License: Apache-2
Platform: UNKNOWN
